sbbst/__init__.py
sbbst-1.0.dist-info/LICENSE.txt
sbbst-1.0.dist-info/METADATA
sbbst-1.0.dist-info/WHEEL
sbbst-1.0.dist-info/top_level.txt
sbbst-1.0.dist-info/RECORD
