Metadata-Version: 2.1
Name: sbbst
Version: 1.0
Summary: A Python implementation of a self balancing binary search tree (AVL Tree). Useful to practice, study and see how a SBBST works.
Home-page: https://github.com/Ualabi/self_balancing_binary_search_tree
Author: Joseandres Hinojoza
Author-email: jhinojoza@outlook.com
License: MIT
Keywords: Self Balancing Binary Search Tree,Balanced Binary Search Tree,Binary Search Tree,Binary Tree,AVL Tree,SBBST,BBST,BST,Print Tree,sbbst
Platform: UNKNOWN
Classifier: Development Status :: 5 - Production/Stable
Classifier: Intended Audience :: Developers
Classifier: Intended Audience :: Education
Classifier: Operating System :: Unix
Classifier: Operating System :: MacOS
Classifier: Operating System :: Microsoft :: Windows
Classifier: License :: OSI Approved :: MIT License
Classifier: Programming Language :: Python
Classifier: Programming Language :: Python :: 2
Classifier: Programming Language :: Python :: 3
Classifier: Topic :: Education
